{
  "$schema": "https://mintlify.com/schema.json",
  "name": "Your Documentation",
  "theme": "mint",
  "logo": {
    "dark": "/logo/dark.svg",
    "light": "/logo/light.svg"
  },
  "favicon": "/favicon.svg",
  "colors": {
    "primary": "#007BFF",
    "light": "#4DABFF",
    "dark": "#005BC4",
    "background": {
      "light": "#F9FAFB",
      "dark": "#111827"
    },
    "anchors": {
      "from": "#007BFF",
      "to": "#4DABFF"
    }
  },
  "modeToggle": {
    "default": "light",
    "isHidden": false
  },
  "topbarLinks": [
    {
      "name": "Support",
      "url": "https://support.yourdomain.com"
    }
  ],
  "topbarCtaButton": {
    "name": "Get Started",
    "url": "/getting-started"
  },
  "tabs": [
    {
      "name": "Getting Started",
      "url": "getting-started"
    },
    {
      "name": "Webhooks",
      "url": "webhooks"
    },
    {
      "name": "Access API",
      "url": "access-api"
    },
    {
      "name": "AuthKit SDK",
      "url": "authkit-sdk"
    },
    {
      "name": "EnrollKit SDK",
      "url": "enrollkit-sdk"
    },
    {
      "name": "Trust Center",
      "url": "trust-center"
    }
  ],
  "navigation": [
    {
      "group": "Getting Started",
      "pages": [
        "getting-started/introduction"
      ]
    },
    {
      "group": "Webhooks",
      "pages": [
        "webhooks/overview"
      ]
    },
    {
      "group": "Access API",
      "pages": [
        "access-api/reference"
      ]
    },
    {
      "group": "AuthKit SDK",
      "pages": [
        "authkit-sdk/guide"
      ]
    },
    {
      "group": "EnrollKit SDK",
      "pages": [
        "enrollkit-sdk/guide"
      ]
    },
    {
      "group": "Trust Center",
      "pages": [
        {
          "page": "Trust Center",
          "url": "https://trust.wicketsoft.com"
        }
      ]
    }
  ],
  "anchors": [
    {
      "name": "Ticketing",
      "url": "/webhooks/overview#ticketing",
      "group": "Webhooks"
    },
    {
      "name": "Credentialing",
      "url": "/webhooks/overview#credentialing",
      "group": "Webhooks"
    },
    {
      "name": "Interactions",
      "url": "/webhooks/overview#interactions",
      "group": "Webhooks"
    },
    {
      "name": "iOS",
      "url": "/authkit-sdk/guide#ios",
      "group": "AuthKit SDK"
    },
    {
      "name": "Android",
      "url": "/authkit-sdk/guide#android",
      "group": "AuthKit SDK"
    },
    {
      "name": "iOS",
      "url": "/enrollkit-sdk/guide#ios",
      "group": "EnrollKit SDK"
    },
    {
      "name": "Android",
      "url": "/enrollkit-sdk/guide#android",
      "group": "EnrollKit SDK"
    },
    {
      "name": "React",
      "url": "/enrollkit-sdk/guide#react",
      "group": "EnrollKit SDK"
    },
    {
      "name": "Web",
      "url": "/enrollkit-sdk/guide#web",
      "group": "EnrollKit SDK"
    }
  ]
}